{
  "id": "206247b6-9fec-4ed2-8927-e4f388c674d4",
  "revision": 0,
  "last_node_id": 128,
  "last_link_id": 209,
  "nodes": [
    {
      "id": 91,
      "type": "GetImageSizeAndCount",
      "pos": [
        -664.0637704523859,
        596.3432885406949
      ],
      "size": [
        190.86484375,
        86
      ],
      "flags": {},
      "order": 32,
      "mode": 0,
      "inputs": [
        {
          "name": "image",
          "type": "IMAGE",
          "link": 129
        }
      ],
      "outputs": [
        {
          "name": "image",
          "type": "IMAGE",
          "links": [
            133
          ]
        },
        {
          "label": "480 width",
          "name": "width",
          "type": "INT",
          "links": [
            156
          ]
        },
        {
          "label": "832 height",
          "name": "height",
          "type": "INT",
          "links": [
            158
          ]
        },
        {
          "label": "168 count",
          "name": "count",
          "type": "INT",
          "links": [
            132
          ]
        }
      ],
      "properties": {
        "cnr_id": "comfyui-kjnodes",
        "ver": "f37df472dfb325f1f72c90e2df56e72f40f850f0",
        "Node name for S&R": "GetImageSizeAndCount",
        "ue_properties": {
          "widget_ue_connectable": {},
          "version": "7.5.1",
          "input_ue_unconnectable": {}
        }
      },
      "widgets_values": []
    },
    {
      "id": 103,
      "type": "GetNode",
      "pos": [
        -733.7633203429151,
        -144.11823888879903
      ],
      "size": [
        210,
        34
      ],
      "flags": {
        "collapsed": true
      },
      "order": 0,
      "mode": 0,
      "inputs": [],
      "outputs": [
        {
          "name": "INT",
          "type": "INT",
          "links": [
            164
          ]
        }
      ],
      "title": "Get_height",
      "properties": {
        "ue_properties": {
          "widget_ue_connectable": {},
          "version": "7.5.1",
          "input_ue_unconnectable": {}
        }
      },
      "widgets_values": [
        "height"
      ],
      "color": "#1b4669",
      "bgcolor": "#29699c"
    },
    {
      "id": 104,
      "type": "GetNode",
      "pos": [
        -230.44208918212954,
        -65.4818789984162
      ],
      "size": [
        210,
        34
      ],
      "flags": {
        "collapsed": true
      },
      "order": 1,
      "mode": 0,
      "inputs": [],
      "outputs": [
        {
          "name": "INT",
          "type": "INT",
          "links": [
            165
          ]
        }
      ],
      "title": "Get_width",
      "properties": {
        "ue_properties": {
          "widget_ue_connectable": {},
          "version": "7.5.1",
          "input_ue_unconnectable": {}
        }
      },
      "widgets_values": [
        "width"
      ],
      "color": "#1b4669",
      "bgcolor": "#29699c"
    },
    {
      "id": 105,
      "type": "GetNode",
      "pos": [
        -231.53217572009217,
        -18.609555029019994
      ],
      "size": [
        210,
        34
      ],
      "flags": {
        "collapsed": true
      },
      "order": 2,
      "mode": 0,
      "inputs": [],
      "outputs": [
        {
          "name": "INT",
          "type": "INT",
          "links": [
            166
          ]
        }
      ],
      "title": "Get_height",
      "properties": {
        "ue_properties": {
          "widget_ue_connectable": {},
          "version": "7.5.1",
          "input_ue_unconnectable": {}
        }
      },
      "widgets_values": [
        "height"
      ],
      "color": "#1b4669",
      "bgcolor": "#29699c"
    },
    {
      "id": 82,
      "type": "WanVideoClipVisionEncode",
      "pos": [
        940.2580703822103,
        874.3085592043358
      ],
      "size": [
        327.5999755859375,
        262
      ],
      "flags": {
        "collapsed": true
      },
      "order": 46,
      "mode": 0,
      "inputs": [
        {
          "name": "clip_vision",
          "type": "CLIP_VISION",
          "link": 171
        },
        {
          "name": "image_1",
          "type": "IMAGE",
          "link": 114
        },
        {
          "name": "image_2",
          "shape": 7,
          "type": "IMAGE",
          "link": null
        },
        {
          "name": "negative_image",
          "shape": 7,
          "type": "IMAGE",
          "link": null
        }
      ],
      "outputs": [
        {
          "name": "image_embeds",
          "type": "WANVIDIMAGE_CLIPEMBEDS",
          "links": [
            115
          ]
        }
      ],
      "properties": {
        "cnr_id": "ComfyUI-WanVideoWrapper",
        "ver": "d9b1f4d1a5aea91d101ae97a54714a5861af3f50",
        "Node name for S&R": "WanVideoClipVisionEncode",
        "ue_properties": {
          "widget_ue_connectable": {},
          "version": "7.5.1",
          "input_ue_unconnectable": {}
        }
      },
      "widgets_values": [
        1,
        1,
        "center",
        "average",
        true,
        0,
        0.20000000000000004
      ],
      "color": "#233",
      "bgcolor": "#355"
    },
    {
      "id": 28,
      "type": "WanVideoDecode",
      "pos": [
        1605.6112420868067,
        -655.6036362809716
      ],
      "size": [
        315,
        198
      ],
      "flags": {},
      "order": 50,
      "mode": 0,
      "inputs": [
        {
          "name": "vae",
          "type": "WANVAE",
          "link": 174
        },
        {
          "name": "samples",
          "type": "LATENT",
          "link": 195
        }
      ],
      "outputs": [
        {
          "name": "images",
          "type": "IMAGE",
          "slot_index": 0,
          "links": [
            179
          ]
        }
      ],
      "properties": {
        "cnr_id": "ComfyUI-WanVideoWrapper",
        "ver": "d9b1f4d1a5aea91d101ae97a54714a5861af3f50",
        "Node name for S&R": "WanVideoDecode",
        "ue_properties": {
          "widget_ue_connectable": {},
          "version": "7.5.1",
          "input_ue_unconnectable": {}
        }
      },
      "widgets_values": [
        false,
        272,
        272,
        144,
        128,
        "default"
      ],
      "color": "#322",
      "bgcolor": "#533"
    },
    {
      "id": 114,
      "type": "GetNode",
      "pos": [
        1795.0266377964203,
        -744.7427387327818
      ],
      "size": [
        210,
        50
      ],
      "flags": {
        "collapsed": true
      },
      "order": 3,
      "mode": 0,
      "inputs": [],
      "outputs": [
        {
          "name": "IMAGE",
          "type": "IMAGE",
          "links": [
            177
          ]
        }
      ],
      "title": "Get_poses",
      "properties": {
        "ue_properties": {
          "widget_ue_connectable": {},
          "version": "7.5.1",
          "input_ue_unconnectable": {}
        }
      },
      "widgets_values": [
        "poses"
      ],
      "color": "#2a363b",
      "bgcolor": "#3f5159"
    },
    {
      "id": 79,
      "type": "ImageConcatMulti",
      "pos": [
        1972.027527964287,
        -740.4807419241877
      ],
      "size": [
        261.2797068857276,
        170
      ],
      "flags": {
        "collapsed": true
      },
      "order": 31,
      "mode": 0,
      "inputs": [
        {
          "name": "image_1",
          "type": "IMAGE",
          "link": 155
        },
        {
          "name": "image_2",
          "shape": 7,
          "type": "IMAGE",
          "link": 177
        }
      ],
      "outputs": [
        {
          "name": "images",
          "type": "IMAGE",
          "links": [
            180
          ]
        }
      ],
      "properties": {
        "cnr_id": "comfyui-kjnodes",
        "ver": "f37df472dfb325f1f72c90e2df56e72f40f850f0",
        "ue_properties": {
          "widget_ue_connectable": {},
          "version": "7.5.1",
          "input_ue_unconnectable": {}
        }
      },
      "widgets_values": [
        2,
        "down",
        false,
        null
      ]
    },
    {
      "id": 39,
      "type": "WanVideoBlockSwap",
      "pos": [
        -262.8103146556545,
        -1318.1035951069507
      ],
      "size": [
        315,
        202
      ],
      "flags": {},
      "order": 4,
      "mode": 0,
      "inputs": [],
      "outputs": [
        {
          "name": "block_swap_args",
          "type": "BLOCKSWAPARGS",
          "slot_index": 0,
          "links": [
            92
          ]
        }
      ],
      "properties": {
        "cnr_id": "ComfyUI-WanVideoWrapper",
        "ver": "d9b1f4d1a5aea91d101ae97a54714a5861af3f50",
        "Node name for S&R": "WanVideoBlockSwap",
        "ue_properties": {
          "widget_ue_connectable": {},
          "version": "7.5.1",
          "input_ue_unconnectable": {}
        }
      },
      "widgets_values": [
        35,
        false,
        false,
        true,
        0,
        1,
        false
      ],
      "color": "#223",
      "bgcolor": "#335"
    },
    {
      "id": 70,
      "type": "WanVideoSetBlockSwap",
      "pos": [
        -267.2797667623184,
        -1043.59269546829
      ],
      "size": [
        201.7681640625,
        46
      ],
      "flags": {},
      "order": 33,
      "mode": 0,
      "inputs": [
        {
          "name": "model",
          "type": "WANVIDEOMODEL",
          "link": 90
        },
        {
          "name": "block_swap_args",
          "shape": 7,
          "type": "BLOCKSWAPARGS",
          "link": 92
        }
      ],
      "outputs": [
        {
          "name": "model",
          "type": "WANVIDEOMODEL",
          "links": [
            104
          ]
        }
      ],
      "properties": {
        "cnr_id": "ComfyUI-WanVideoWrapper",
        "ver": "5406a72f62adf4a31a8a0a0e4923cc5288399652",
        "Node name for S&R": "WanVideoSetBlockSwap",
        "ue_properties": {
          "widget_ue_connectable": {},
          "version": "7.5.1",
          "input_ue_unconnectable": {}
        }
      },
      "widgets_values": [],
      "color": "#223",
      "bgcolor": "#335"
    },
    {
      "id": 108,
      "type": "SetNode",
      "pos": [
        -418.8157817947404,
        -714.7388879398823
      ],
      "size": [
        210,
        60
      ],
      "flags": {
        "collapsed": true
      },
      "order": 29,
      "mode": 0,
      "inputs": [
        {
          "name": "WANVAE",
          "type": "WANVAE",
          "link": 172
        }
      ],
      "outputs": [
        {
          "name": "*",
          "type": "*",
          "links": []
        }
      ],
      "title": "Set_VAE",
      "properties": {
        "previousName": "VAE",
        "ue_properties": {
          "widget_ue_connectable": {},
          "version": "7.5.1",
          "input_ue_unconnectable": {}
        }
      },
      "widgets_values": [
        "VAE"
      ],
      "color": "#322",
      "bgcolor": "#533"
    },
    {
      "id": 109,
      "type": "GetNode",
      "pos": [
        1456.8216683691237,
        -622.4945266259768
      ],
      "size": [
        210,
        60
      ],
      "flags": {
        "collapsed": true
      },
      "order": 5,
      "mode": 0,
      "inputs": [],
      "outputs": [
        {
          "name": "WANVAE",
          "type": "WANVAE",
          "links": [
            174
          ]
        }
      ],
      "title": "Get_VAE",
      "properties": {
        "ue_properties": {
          "widget_ue_connectable": {},
          "version": "7.5.1",
          "input_ue_unconnectable": {}
        }
      },
      "widgets_values": [
        "VAE"
      ],
      "color": "#322",
      "bgcolor": "#533"
    },
    {
      "id": 116,
      "type": "GetNode",
      "pos": [
        -207.20489811745227,
        -206.43232509553354
      ],
      "size": [
        210,
        34
      ],
      "flags": {
        "collapsed": true
      },
      "order": 6,
      "mode": 0,
      "inputs": [],
      "outputs": [
        {
          "name": "WANVAE",
          "type": "WANVAE",
          "links": [
            182
          ]
        }
      ],
      "title": "Get_VAE",
      "properties": {
        "ue_properties": {
          "widget_ue_connectable": {},
          "version": "7.5.1",
          "input_ue_unconnectable": {}
        }
      },
      "widgets_values": [
        "VAE"
      ],
      "color": "#322",
      "bgcolor": "#533"
    },
    {
      "id": 81,
      "type": "GetImageRangeFromBatch",
      "pos": [
        945.0538803083613,
        926.2278660836186
      ],
      "size": [
        340.3267578125,
        102
      ],
      "flags": {
        "collapsed": true
      },
      "order": 45,
      "mode": 0,
      "inputs": [
        {
          "name": "images",
          "shape": 7,
          "type": "IMAGE",
          "link": 186
        },
        {
          "name": "masks",
          "shape": 7,
          "type": "MASK",
          "link": null
        }
      ],
      "outputs": [
        {
          "name": "IMAGE",
          "type": "IMAGE",
          "links": [
            114
          ]
        },
        {
          "name": "MASK",
          "type": "MASK",
          "links": null
        }
      ],
      "properties": {
        "cnr_id": "comfyui-kjnodes",
        "ver": "f37df472dfb325f1f72c90e2df56e72f40f850f0",
        "Node name for S&R": "GetImageRangeFromBatch",
        "ue_properties": {
          "widget_ue_connectable": {},
          "version": "7.5.1",
          "input_ue_unconnectable": {}
        }
      },
      "widgets_values": [
        0,
        1
      ]
    },
    {
      "id": 72,
      "type": "WanVideoEncode",
      "pos": [
        623.2410903688957,
        572.1071945906087
      ],
      "size": [
        270,
        242
      ],
      "flags": {},
      "order": 44,
      "mode": 0,
      "inputs": [
        {
          "name": "vae",
          "type": "WANVAE",
          "link": 175
        },
        {
          "name": "image",
          "type": "IMAGE",
          "link": 185
        },
        {
          "name": "mask",
          "shape": 7,
          "type": "MASK",
          "link": null
        }
      ],
      "outputs": [
        {
          "name": "samples",
          "type": "LATENT",
          "links": [
            102
          ]
        }
      ],
      "properties": {
        "cnr_id": "ComfyUI-WanVideoWrapper",
        "ver": "772642b4f132a077f655ff24d11cb99ef108aff5",
        "Node name for S&R": "WanVideoEncode",
        "ue_properties": {
          "widget_ue_connectable": {},
          "version": "7.5.1",
          "input_ue_unconnectable": {}
        }
      },
      "widgets_values": [
        false,
        272,
        272,
        144,
        128,
        0,
        1
      ],
      "color": "#322",
      "bgcolor": "#533"
    },
    {
      "id": 112,
      "type": "GetNode",
      "pos": [
        635.4993624450752,
        524.546576932489
      ],
      "size": [
        210,
        34
      ],
      "flags": {
        "collapsed": true
      },
      "order": 7,
      "mode": 0,
      "inputs": [],
      "outputs": [
        {
          "name": "WANVAE",
          "type": "WANVAE",
          "links": [
            175
          ]
        }
      ],
      "title": "Get_VAE",
      "properties": {
        "ue_properties": {
          "widget_ue_connectable": {},
          "version": "7.5.1",
          "input_ue_unconnectable": {}
        }
      },
      "widgets_values": [
        "VAE"
      ],
      "color": "#322",
      "bgcolor": "#533"
    },
    {
      "id": 78,
      "type": "WanVideoSetLoRAs",
      "pos": [
        187.88410531738057,
        -997.8689830032076
      ],
      "size": [
        174.5337890625,
        46
      ],
      "flags": {},
      "order": 37,
      "mode": 0,
      "inputs": [
        {
          "name": "model",
          "type": "WANVIDEOMODEL",
          "link": 104
        },
        {
          "name": "lora",
          "shape": 7,
          "type": "WANVIDLORA",
          "link": 106
        }
      ],
      "outputs": [
        {
          "name": "model",
          "type": "WANVIDEOMODEL",
          "links": [
            192
          ]
        }
      ],
      "properties": {
        "cnr_id": "ComfyUI-WanVideoWrapper",
        "ver": "772642b4f132a077f655ff24d11cb99ef108aff5",
        "Node name for S&R": "WanVideoSetLoRAs",
        "ue_properties": {
          "widget_ue_connectable": {},
          "version": "7.5.1",
          "input_ue_unconnectable": {}
        }
      },
      "widgets_values": [],
      "color": "#223",
      "bgcolor": "#335"
    },
    {
      "id": 87,
      "type": "WanVideoContextOptions",
      "pos": [
        855.077517790794,
        -538.2635362112408
      ],
      "size": [
        275.783203125,
        202
      ],
      "flags": {},
      "order": 8,
      "mode": 0,
      "inputs": [
        {
          "name": "reference_latent",
          "shape": 7,
          "type": "LATENT",
          "link": null
        }
      ],
      "outputs": [
        {
          "name": "context_options",
          "type": "WANVIDCONTEXT",
          "links": [
            193
          ]
        }
      ],
      "properties": {
        "cnr_id": "ComfyUI-WanVideoWrapper",
        "ver": "394c7c13d24e5d3378e8259f9c2f9d33c49d985f",
        "Node name for S&R": "WanVideoContextOptions",
        "ue_properties": {
          "widget_ue_connectable": {},
          "version": "7.5.1",
          "input_ue_unconnectable": {}
        }
      },
      "widgets_values": [
        "uniform_standard",
        81,
        4,
        16,
        true,
        false,
        "linear"
      ]
    },
    {
      "id": 123,
      "type": "PrimitiveNode",
      "pos": [
        845.7007526254484,
        -13.41171771418989
      ],
      "size": [
        210,
        82
      ],
      "flags": {},
      "order": 9,
      "mode": 0,
      "inputs": [],
      "outputs": [
        {
          "name": "FLOAT",
          "type": "FLOAT",
          "widget": {
            "name": "cfg"
          },
          "links": [
            205
          ]
        }
      ],
      "title": "cfg",
      "properties": {
        "Run widget replace on values": false,
        "ue_properties": {
          "widget_ue_connectable": {},
          "version": "7.5.1",
          "input_ue_unconnectable": {}
        }
      },
      "widgets_values": [
        1,
        "fixed"
      ]
    },
    {
      "id": 119,
      "type": "WanVideoSamplerSettings",
      "pos": [
        894.5619671678012,
        -104.9760927796988
      ],
      "size": [
        309.1171875,
        690
      ],
      "flags": {
        "collapsed": true
      },
      "order": 48,
      "mode": 0,
      "inputs": [
        {
          "name": "model",
          "type": "WANVIDEOMODEL",
          "link": 192
        },
        {
          "name": "image_embeds",
          "type": "WANVIDIMAGE_EMBEDS",
          "link": 194
        },
        {
          "name": "text_embeds",
          "shape": 7,
          "type": "WANVIDEOTEXTEMBEDS",
          "link": 196
        },
        {
          "name": "samples",
          "shape": 7,
          "type": "LATENT",
          "link": null
        },
        {
          "name": "feta_args",
          "shape": 7,
          "type": "FETAARGS",
          "link": null
        },
        {
          "name": "context_options",
          "shape": 7,
          "type": "WANVIDCONTEXT",
          "link": 193
        },
        {
          "name": "cache_args",
          "shape": 7,
          "type": "CACHEARGS",
          "link": null
        },
        {
          "name": "flowedit_args",
          "shape": 7,
          "type": "FLOWEDITARGS",
          "link": null
        },
        {
          "name": "slg_args",
          "shape": 7,
          "type": "SLGARGS",
          "link": null
        },
        {
          "name": "loop_args",
          "shape": 7,
          "type": "LOOPARGS",
          "link": null
        },
        {
          "name": "experimental_args",
          "shape": 7,
          "type": "EXPERIMENTALARGS",
          "link": null
        },
        {
          "name": "sigmas",
          "shape": 7,
          "type": "SIGMAS",
          "link": null
        },
        {
          "name": "unianimate_poses",
          "shape": 7,
          "type": "UNIANIMATE_POSE",
          "link": null
        },
        {
          "name": "fantasytalking_embeds",
          "shape": 7,
          "type": "FANTASYTALKING_EMBEDS",
          "link": null
        },
        {
          "name": "uni3c_embeds",
          "shape": 7,
          "type": "UNI3C_EMBEDS",
          "link": null
        },
        {
          "name": "multitalk_embeds",
          "shape": 7,
          "type": "MULTITALK_EMBEDS",
          "link": null
        },
        {
          "name": "freeinit_args",
          "shape": 7,
          "type": "FREEINITARGS",
          "link": null
        },
        {
          "name": "cfg",
          "type": "FLOAT",
          "widget": {
            "name": "cfg"
          },
          "link": 205
        },
        {
          "name": "seed",
          "type": "INT",
          "widget": {
            "name": "seed"
          },
          "link": 207
        },
        {
          "name": "scheduler",
          "type": "COMBO",
          "widget": {
            "name": "scheduler"
          },
          "link": 206
        }
      ],
      "outputs": [
        {
          "name": "sampler_inputs",
          "type": "SAMPLER_ARGS",
          "links": [
            191
          ]
        }
      ],
      "properties": {
        "cnr_id": "ComfyUI-WanVideoWrapper",
        "ver": "394c7c13d24e5d3378e8259f9c2f9d33c49d985f",
        "Node name for S&R": "WanVideoSamplerSettings",
        "ue_properties": {
          "widget_ue_connectable": {
            "cfg": true,
            "seed": true,
            "scheduler": true
          },
          "version": "7.5.1",
          "input_ue_unconnectable": {}
        }
      },
      "widgets_values": [
        4,
        1,
        5,
        230951159472333,
        "fixed",
        true,
        "dpm++_sde",
        0,
        1,
        false,
        "comfy",
        0,
        -1,
        false
      ]
    },
    {
      "id": 115,
      "type": "ImageConcatMulti",
      "pos": [
        1966.034363762838,
        -688.6455293008553
      ],
      "size": [
        261.2797068857276,
        170
      ],
      "flags": {
        "collapsed": false
      },
      "order": 51,
      "mode": 0,
      "inputs": [
        {
          "name": "image_1",
          "type": "IMAGE",
          "link": 179
        },
        {
          "name": "image_2",
          "shape": 7,
          "type": "IMAGE",
          "link": 180
        }
      ],
      "outputs": [
        {
          "name": "images",
          "type": "IMAGE",
          "links": [
            181
          ]
        }
      ],
      "properties": {
        "cnr_id": "comfyui-kjnodes",
        "ver": "f37df472dfb325f1f72c90e2df56e72f40f850f0",
        "ue_properties": {
          "widget_ue_connectable": {},
          "version": "7.5.1",
          "input_ue_unconnectable": {}
        }
      },
      "widgets_values": [
        2,
        "left",
        true,
        null
      ]
    },
    {
      "id": 122,
      "type": "WanVideoScheduler",
      "pos": [
        1145.4126272117978,
        -537.9307646338074
      ],
      "size": [
        296.1612785322477,
        459.8775846555228
      ],
      "flags": {},
      "order": 10,
      "mode": 0,
      "inputs": [
        {
          "name": "sigmas",
          "shape": 7,
          "type": "SIGMAS",
          "link": null
        }
      ],
      "outputs": [
        {
          "name": "sigmas",
          "type": "SIGMAS",
          "links": []
        },
        {
          "name": "steps",
          "type": "INT",
          "links": []
        },
        {
          "name": "shift",
          "type": "FLOAT",
          "links": []
        },
        {
          "name": "scheduler",
          "type": "COMBO",
          "links": [
            206
          ]
        },
        {
          "name": "start_step",
          "type": "INT",
          "links": []
        },
        {
          "name": "end_step",
          "type": "INT",
          "links": []
        }
      ],
      "properties": {
        "cnr_id": "ComfyUI-WanVideoWrapper",
        "ver": "394c7c13d24e5d3378e8259f9c2f9d33c49d985f",
        "Node name for S&R": "WanVideoScheduler",
        "ue_properties": {
          "widget_ue_connectable": {},
          "version": "7.5.1",
          "input_ue_unconnectable": {}
        }
      },
      "widgets_values": [
        "dpm++_sde",
        4,
        5,
        0,
        -1,
        ""
      ]
    },
    {
      "id": 118,
      "type": "WanVideoSamplerFromSettings",
      "pos": [
        1497.3310308258558,
        -339.08256525853756
      ],
      "size": [
        734.7520165037962,
        1306.9034952732468
      ],
      "flags": {},
      "order": 49,
      "mode": 0,
      "inputs": [
        {
          "name": "sampler_inputs",
          "type": "SAMPLER_ARGS",
          "link": 191
        }
      ],
      "outputs": [
        {
          "name": "samples",
          "type": "LATENT",
          "links": [
            195
          ]
        },
        {
          "name": "denoised_samples",
          "type": "LATENT",
          "links": null
        }
      ],
      "properties": {
        "cnr_id": "ComfyUI-WanVideoWrapper",
        "ver": "394c7c13d24e5d3378e8259f9c2f9d33c49d985f",
        "Node name for S&R": "WanVideoSamplerFromSettings",
        "ue_properties": {
          "widget_ue_connectable": {},
          "version": "7.5.1",
          "input_ue_unconnectable": {}
        }
      },
      "widgets_values": []
    },
    {
      "id": 83,
      "type": "VHS_VideoCombine",
      "pos": [
        2308.9617297797527,
        -689.7735531694796
      ],
      "size": [
        733.1427431068323,
        1172.0760587012282
      ],
      "flags": {},
      "order": 52,
      "mode": 0,
      "inputs": [
        {
          "name": "images",
          "type": "IMAGE",
          "link": 181
        },
        {
          "name": "audio",
          "shape": 7,
          "type": "AUDIO",
          "link": null
        },
        {
          "name": "meta_batch",
          "shape": 7,
          "type": "VHS_BatchManager",
          "link": null
        },
        {
          "name": "vae",
          "shape": 7,
          "type": "VAE",
          "link": null
        }
      ],
      "outputs": [
        {
          "name": "Filenames",
          "type": "VHS_FILENAMES",
          "links": null
        }
      ],
      "properties": {
        "cnr_id": "comfyui-videohelpersuite",
        "ver": "0a75c7958fe320efcb052f1d9f8451fd20c730a8",
        "Node name for S&R": "VHS_VideoCombine",
        "ue_properties": {
          "widget_ue_connectable": {},
          "version": "7.5.1",
          "input_ue_unconnectable": {}
        }
      },
      "widgets_values": {
        "frame_rate": 24,
        "loop_count": 0,
        "filename_prefix": "WanVideoWrapper_SteadyDancer",
        "format": "video/h264-mp4",
        "pix_fmt": "yuv420p",
        "crf": 19,
        "save_metadata": true,
        "trim_to_audio": false,
        "pingpong": false,
        "save_output": true,
        "videopreview": {
          "hidden": false,
          "paused": false,
          "params": {
            "filename": "WanVideoWrapper_SteadyDancer_00005.mp4",
            "subfolder": "",
            "type": "output",
            "format": "video/h264-mp4",
            "frame_rate": 24,
            "workflow": "WanVideoWrapper_SteadyDancer_00005.png",
            "fullpath": "E:\\staging\\ComfyTest\\ComfyUI\\output\\WanVideoWrapper_SteadyDancer_00005.mp4"
          }
        }
      }
    },
    {
      "id": 59,
      "type": "CLIPVisionLoader",
      "pos": [
        -243.41497093211427,
        -718.0849119529955
      ],
      "size": [
        315,
        58
      ],
      "flags": {},
      "order": 12,
      "mode": 0,
      "inputs": [],
      "outputs": [
        {
          "name": "CLIP_VISION",
          "type": "CLIP_VISION",
          "links": [
            169
          ]
        }
      ],
      "properties": {
        "cnr_id": "comfy-core",
        "ver": "0.3.26",
        "Node name for S&R": "CLIPVisionLoader",
        "ue_properties": {
          "widget_ue_connectable": {},
          "version": "7.5.1",
          "input_ue_unconnectable": {}
        }
      },
      "widgets_values": [
        "clip_vision_h.safetensors"
      ],
      "color": "#233",
      "bgcolor": "#355"
    },
    {
      "id": 106,
      "type": "SetNode",
      "pos": [
        122.2791041740774,
        -688.9258825994664
      ],
      "size": [
        210,
        60
      ],
      "flags": {
        "collapsed": true
      },
      "order": 28,
      "mode": 0,
      "inputs": [
        {
          "name": "CLIP_VISION",
          "type": "CLIP_VISION",
          "link": 169
        }
      ],
      "outputs": [
        {
          "name": "*",
          "type": "*",
          "links": []
        }
      ],
      "title": "Set_clip_vision",
      "properties": {
        "previousName": "clip_vision",
        "ue_properties": {
          "widget_ue_connectable": {},
          "version": "7.5.1",
          "input_ue_unconnectable": {}
        }
      },
      "widgets_values": [
        "clip_vision"
      ]
    },
    {
      "id": 107,
      "type": "GetNode",
      "pos": [
        943.9849108453217,
        829.4344804869705
      ],
      "size": [
        210,
        60
      ],
      "flags": {
        "collapsed": true
      },
      "order": 13,
      "mode": 0,
      "inputs": [],
      "outputs": [
        {
          "name": "CLIP_VISION",
          "type": "CLIP_VISION",
          "links": [
            171
          ]
        }
      ],
      "title": "Get_clip_vision",
      "properties": {
        "ue_properties": {
          "widget_ue_connectable": {},
          "version": "7.5.1",
          "input_ue_unconnectable": {}
        }
      },
      "widgets_values": [
        "clip_vision"
      ]
    },
    {
      "id": 65,
      "type": "WanVideoClipVisionEncode",
      "pos": [
        -52.52334848763119,
        -276.8531019980348
      ],
      "size": [
        327.5999755859375,
        262
      ],
      "flags": {
        "collapsed": true
      },
      "order": 38,
      "mode": 0,
      "inputs": [
        {
          "name": "clip_vision",
          "type": "CLIP_VISION",
          "link": 208
        },
        {
          "name": "image_1",
          "type": "IMAGE",
          "link": 209
        },
        {
          "name": "image_2",
          "shape": 7,
          "type": "IMAGE",
          "link": null
        },
        {
          "name": "negative_image",
          "shape": 7,
          "type": "IMAGE",
          "link": null
        }
      ],
      "outputs": [
        {
          "name": "image_embeds",
          "type": "WANVIDIMAGE_CLIPEMBEDS",
          "links": [
            82
          ]
        }
      ],
      "properties": {
        "cnr_id": "ComfyUI-WanVideoWrapper",
        "ver": "d9b1f4d1a5aea91d101ae97a54714a5861af3f50",
        "Node name for S&R": "WanVideoClipVisionEncode",
        "ue_properties": {
          "widget_ue_connectable": {},
          "version": "7.5.1",
          "input_ue_unconnectable": {}
        }
      },
      "widgets_values": [
        1,
        1,
        "center",
        "average",
        true,
        0,
        0.20000000000000004
      ],
      "color": "#233",
      "bgcolor": "#355"
    },
    {
      "id": 128,
      "type": "GetNode",
      "pos": [
        -52.37740667628973,
        -337.8157950215469
      ],
      "size": [
        210,
        50
      ],
      "flags": {
        "collapsed": true
      },
      "order": 14,
      "mode": 0,
      "inputs": [],
      "outputs": [
        {
          "name": "CLIP_VISION",
          "type": "CLIP_VISION",
          "links": [
            208
          ]
        }
      ],
      "title": "Get_clip_vision",
      "properties": {
        "ue_properties": {
          "widget_ue_connectable": {},
          "version": "7.5.1",
          "input_ue_unconnectable": {}
        }
      },
      "widgets_values": [
        "clip_vision"
      ],
      "color": "#233",
      "bgcolor": "#355"
    },
    {
      "id": 96,
      "type": "SetNode",
      "pos": [
        -245.63704325189582,
        -272.9625985324547
      ],
      "size": [
        210,
        60
      ],
      "flags": {
        "collapsed": true
      },
      "order": 34,
      "mode": 0,
      "inputs": [
        {
          "name": "IMAGE",
          "type": "IMAGE",
          "link": 153
        }
      ],
      "outputs": [
        {
          "name": "IMAGE",
          "type": "IMAGE",
          "links": [
            154,
            209
          ]
        }
      ],
      "title": "Set_start_frame",
      "properties": {
        "previousName": "start_frame",
        "ue_properties": {
          "widget_ue_connectable": {},
          "version": "7.5.1",
          "input_ue_unconnectable": {}
        }
      },
      "widgets_values": [
        "start_frame"
      ],
      "color": "#2a363b",
      "bgcolor": "#3f5159"
    },
    {
      "id": 68,
      "type": "ImageResizeKJv2",
      "pos": [
        -574.7846430836909,
        -287.8351187717786
      ],
      "size": [
        270,
        336
      ],
      "flags": {},
      "order": 30,
      "mode": 0,
      "inputs": [
        {
          "name": "image",
          "type": "IMAGE",
          "link": 122
        },
        {
          "name": "mask",
          "shape": 7,
          "type": "MASK",
          "link": null
        },
        {
          "name": "width",
          "type": "INT",
          "widget": {
            "name": "width"
          },
          "link": 163
        },
        {
          "name": "height",
          "type": "INT",
          "widget": {
            "name": "height"
          },
          "link": 164
        }
      ],
      "outputs": [
        {
          "name": "IMAGE",
          "type": "IMAGE",
          "links": [
            153
          ]
        },
        {
          "name": "width",
          "type": "INT",
          "links": []
        },
        {
          "name": "height",
          "type": "INT",
          "links": []
        },
        {
          "name": "mask",
          "type": "MASK",
          "links": null
        }
      ],
      "properties": {
        "cnr_id": "comfyui-kjnodes",
        "ver": "ad37ce656c13e9abea002b46e3a89be3dba32355",
        "Node name for S&R": "ImageResizeKJv2",
        "ue_properties": {
          "widget_ue_connectable": {
            "width": true,
            "height": true
          },
          "version": "7.5.1",
          "input_ue_unconnectable": {}
        }
      },
      "widgets_values": [
        480,
        832,
        "lanczos",
        "crop",
        "0, 0, 0",
        "center",
        16,
        "cpu",
        "<tr><td>Output: </td><td><b>1</b> x <b>480</b> x <b>832 | 4.57MB</b></td></tr>"
      ]
    },
    {
      "id": 102,
      "type": "GetNode",
      "pos": [
        -732.6732338049525,
        -190.99056285819523
      ],
      "size": [
        210,
        34
      ],
      "flags": {
        "collapsed": true
      },
      "order": 15,
      "mode": 0,
      "inputs": [],
      "outputs": [
        {
          "name": "INT",
          "type": "INT",
          "links": [
            163
          ]
        }
      ],
      "title": "Get_width",
      "properties": {
        "ue_properties": {
          "widget_ue_connectable": {},
          "version": "7.5.1",
          "input_ue_unconnectable": {}
        }
      },
      "widgets_values": [
        "width"
      ],
      "color": "#1b4669",
      "bgcolor": "#29699c"
    },
    {
      "id": 63,
      "type": "WanVideoImageToVideoEncode",
      "pos": [
        -55.11665002742402,
        -230.09161728786358
      ],
      "size": [
        352.79998779296875,
        414
      ],
      "flags": {},
      "order": 40,
      "mode": 0,
      "inputs": [
        {
          "name": "vae",
          "shape": 7,
          "type": "WANVAE",
          "link": 182
        },
        {
          "name": "clip_embeds",
          "shape": 7,
          "type": "WANVIDIMAGE_CLIPEMBEDS",
          "link": 82
        },
        {
          "name": "start_image",
          "shape": 7,
          "type": "IMAGE",
          "link": 154
        },
        {
          "name": "end_image",
          "shape": 7,
          "type": "IMAGE",
          "link": null
        },
        {
          "name": "control_embeds",
          "shape": 7,
          "type": "WANVIDIMAGE_EMBEDS",
          "link": null
        },
        {
          "name": "temporal_mask",
          "shape": 7,
          "type": "MASK",
          "link": null
        },
        {
          "name": "extra_latents",
          "shape": 7,
          "type": "LATENT",
          "link": null
        },
        {
          "name": "add_cond_latents",
          "shape": 7,
          "type": "ADD_COND_LATENTS",
          "link": null
        },
        {
          "name": "width",
          "type": "INT",
          "widget": {
            "name": "width"
          },
          "link": 165
        },
        {
          "name": "height",
          "type": "INT",
          "widget": {
            "name": "height"
          },
          "link": 166
        },
        {
          "name": "num_frames",
          "type": "INT",
          "widget": {
            "name": "num_frames"
          },
          "link": 132
        }
      ],
      "outputs": [
        {
          "name": "image_embeds",
          "type": "WANVIDIMAGE_EMBEDS",
          "links": [
            93
          ]
        }
      ],
      "properties": {
        "cnr_id": "ComfyUI-WanVideoWrapper",
        "ver": "d9b1f4d1a5aea91d101ae97a54714a5861af3f50",
        "Node name for S&R": "WanVideoImageToVideoEncode",
        "ue_properties": {
          "widget_ue_connectable": {
            "width": true,
            "height": true,
            "num_frames": true
          },
          "version": "7.5.1",
          "input_ue_unconnectable": {}
        }
      },
      "widgets_values": [
        832,
        480,
        81,
        0,
        1,
        1,
        true,
        true,
        false,
        0
      ],
      "color": "#322",
      "bgcolor": "#533"
    },
    {
      "id": 98,
      "type": "SetNode",
      "pos": [
        -608.5783406197372,
        737.5431642878269
      ],
      "size": [
        210,
        60
      ],
      "flags": {
        "collapsed": true
      },
      "order": 35,
      "mode": 0,
      "inputs": [
        {
          "name": "INT",
          "type": "INT",
          "link": 156
        }
      ],
      "outputs": [
        {
          "name": "INT",
          "type": "INT",
          "links": [
            157,
            167
          ]
        }
      ],
      "title": "Set_width",
      "properties": {
        "previousName": "width",
        "ue_properties": {
          "widget_ue_connectable": {},
          "version": "7.5.1",
          "input_ue_unconnectable": {}
        }
      },
      "widgets_values": [
        "width"
      ],
      "color": "#1b4669",
      "bgcolor": "#29699c"
    },
    {
      "id": 99,
      "type": "SetNode",
      "pos": [
        -609.3413013989538,
        786.2686852704386
      ],
      "size": [
        210,
        60
      ],
      "flags": {
        "collapsed": true
      },
      "order": 36,
      "mode": 0,
      "inputs": [
        {
          "name": "INT",
          "type": "INT",
          "link": 158
        }
      ],
      "outputs": [
        {
          "name": "INT",
          "type": "INT",
          "links": [
            159,
            168
          ]
        }
      ],
      "title": "Set_height",
      "properties": {
        "previousName": "height",
        "ue_properties": {
          "widget_ue_connectable": {},
          "version": "7.5.1",
          "input_ue_unconnectable": {}
        }
      },
      "widgets_values": [
        "height"
      ],
      "color": "#1b4669",
      "bgcolor": "#29699c"
    },
    {
      "id": 89,
      "type": "PoseAndFaceDetection",
      "pos": [
        -435.3912946653781,
        493.90712331342394
      ],
      "size": [
        313.125,
        162
      ],
      "flags": {},
      "order": 39,
      "mode": 0,
      "inputs": [
        {
          "name": "model",
          "type": "POSEMODEL",
          "link": 128
        },
        {
          "name": "images",
          "type": "IMAGE",
          "link": 133
        },
        {
          "name": "retarget_image",
          "shape": 7,
          "type": "IMAGE",
          "link": null
        },
        {
          "name": "width",
          "type": "INT",
          "widget": {
            "name": "width"
          },
          "link": 157
        },
        {
          "name": "height",
          "type": "INT",
          "widget": {
            "name": "height"
          },
          "link": 159
        }
      ],
      "outputs": [
        {
          "name": "pose_data",
          "type": "POSEDATA",
          "links": [
            127
          ]
        },
        {
          "name": "face_images",
          "type": "IMAGE",
          "links": null
        },
        {
          "name": "key_frame_body_points",
          "type": "STRING",
          "links": null
        },
        {
          "name": "bboxes",
          "type": "BBOX",
          "links": null
        },
        {
          "name": "face_bboxes",
          "type": "BBOX,",
          "links": null
        }
      ],
      "properties": {
        "cnr_id": "ComfyUI-WanAnimatePreprocess",
        "ver": "2fcbcae7eec637fdc712fdec18e6266feb8ba3a7",
        "Node name for S&R": "PoseAndFaceDetection"
      },
      "widgets_values": [
        480,
        832
      ]
    },
    {
      "id": 88,
      "type": "DrawViTPose",
      "pos": [
        -413.3661371281176,
        721.1510671358449
      ],
      "size": [
        270,
        178
      ],
      "flags": {},
      "order": 41,
      "mode": 0,
      "inputs": [
        {
          "name": "pose_data",
          "type": "POSEDATA",
          "link": 127
        },
        {
          "name": "width",
          "type": "INT",
          "widget": {
            "name": "width"
          },
          "link": 167
        },
        {
          "name": "height",
          "type": "INT",
          "widget": {
            "name": "height"
          },
          "link": 168
        }
      ],
      "outputs": [
        {
          "name": "pose_images",
          "type": "IMAGE",
          "links": [
            136
          ]
        }
      ],
      "properties": {
        "cnr_id": "ComfyUI-WanAnimatePreprocess",
        "ver": "2fcbcae7eec637fdc712fdec18e6266feb8ba3a7",
        "Node name for S&R": "DrawViTPose"
      },
      "widgets_values": [
        480,
        832,
        16,
        -1,
        -1,
        true
      ]
    },
    {
      "id": 101,
      "type": "GetNode",
      "pos": [
        -71.04055347292368,
        528.0130142002156
      ],
      "size": [
        210,
        50
      ],
      "flags": {
        "collapsed": true
      },
      "order": 16,
      "mode": 0,
      "inputs": [],
      "outputs": [
        {
          "name": "INT",
          "type": "INT",
          "links": [
            162
          ]
        }
      ],
      "title": "Get_width",
      "properties": {
        "ue_properties": {
          "widget_ue_connectable": {},
          "version": "7.5.1",
          "input_ue_unconnectable": {}
        }
      },
      "widgets_values": [
        "width"
      ],
      "color": "#1b4669",
      "bgcolor": "#29699c"
    },
    {
      "id": 77,
      "type": "ImageResizeKJv2",
      "pos": [
        -80.60316588583451,
        581.813193551805
      ],
      "size": [
        270,
        336
      ],
      "flags": {},
      "order": 42,
      "mode": 0,
      "inputs": [
        {
          "name": "image",
          "type": "IMAGE",
          "link": 136
        },
        {
          "name": "mask",
          "shape": 7,
          "type": "MASK",
          "link": null
        },
        {
          "name": "width",
          "type": "INT",
          "widget": {
            "name": "width"
          },
          "link": 162
        },
        {
          "name": "height",
          "type": "INT",
          "widget": {
            "name": "height"
          },
          "link": 161
        }
      ],
      "outputs": [
        {
          "name": "IMAGE",
          "type": "IMAGE",
          "links": [
            176
          ]
        },
        {
          "name": "width",
          "type": "INT",
          "links": []
        },
        {
          "name": "height",
          "type": "INT",
          "links": []
        },
        {
          "name": "mask",
          "type": "MASK",
          "links": null
        }
      ],
      "properties": {
        "cnr_id": "comfyui-kjnodes",
        "ver": "ad37ce656c13e9abea002b46e3a89be3dba32355",
        "Node name for S&R": "ImageResizeKJv2",
        "ue_properties": {
          "widget_ue_connectable": {
            "width": true,
            "height": true
          },
          "version": "7.5.1",
          "input_ue_unconnectable": {}
        }
      },
      "widgets_values": [
        480,
        832,
        "lanczos",
        "crop",
        "0, 0, 0",
        "center",
        16,
        "cpu",
        "<tr><td>Output: </td><td><b>168</b> x <b>480</b> x <b>832 | 767.81MB</b></td></tr>"
      ]
    },
    {
      "id": 100,
      "type": "GetNode",
      "pos": [
        -75.72781580907068,
        482.55786260858605
      ],
      "size": [
        210,
        60
      ],
      "flags": {
        "collapsed": true
      },
      "order": 17,
      "mode": 0,
      "inputs": [],
      "outputs": [
        {
          "name": "INT",
          "type": "INT",
          "links": [
            161
          ]
        }
      ],
      "title": "Get_height",
      "properties": {
        "ue_properties": {
          "widget_ue_connectable": {},
          "version": "7.5.1",
          "input_ue_unconnectable": {}
        }
      },
      "widgets_values": [
        "height"
      ],
      "color": "#1b4669",
      "bgcolor": "#29699c"
    },
    {
      "id": 113,
      "type": "SetNode",
      "pos": [
        66.38261557304351,
        981.6058906702484
      ],
      "size": [
        211.19898541466569,
        60
      ],
      "flags": {
        "collapsed": true
      },
      "order": 43,
      "mode": 0,
      "inputs": [
        {
          "name": "IMAGE",
          "type": "IMAGE",
          "link": 176
        }
      ],
      "outputs": [
        {
          "name": "IMAGE",
          "type": "IMAGE",
          "links": [
            184,
            185,
            186
          ]
        }
      ],
      "title": "Set_poses",
      "properties": {
        "previousName": "poses",
        "ue_properties": {
          "widget_ue_connectable": {},
          "version": "7.5.1",
          "input_ue_unconnectable": {}
        }
      },
      "widgets_values": [
        "poses"
      ],
      "color": "#2a363b",
      "bgcolor": "#3f5159"
    },
    {
      "id": 117,
      "type": "VHS_VideoCombine",
      "pos": [
        236.61945804923013,
        575.4567590988431
      ],
      "size": [
        325.0440446848702,
        876.7430107871083
      ],
      "flags": {},
      "order": 47,
      "mode": 0,
      "inputs": [
        {
          "name": "images",
          "type": "IMAGE",
          "link": 184
        },
        {
          "name": "audio",
          "shape": 7,
          "type": "AUDIO",
          "link": null
        },
        {
          "name": "meta_batch",
          "shape": 7,
          "type": "VHS_BatchManager",
          "link": null
        },
        {
          "name": "vae",
          "shape": 7,
          "type": "VAE",
          "link": null
        }
      ],
      "outputs": [
        {
          "name": "Filenames",
          "type": "VHS_FILENAMES",
          "links": null
        }
      ],
      "properties": {
        "cnr_id": "comfyui-videohelpersuite",
        "ver": "0a75c7958fe320efcb052f1d9f8451fd20c730a8",
        "Node name for S&R": "VHS_VideoCombine",
        "ue_properties": {
          "widget_ue_connectable": {},
          "version": "7.5.1",
          "input_ue_unconnectable": {}
        }
      },
      "widgets_values": {
        "frame_rate": 24,
        "loop_count": 0,
        "filename_prefix": "vitpose",
        "format": "video/h264-mp4",
        "pix_fmt": "yuv420p",
        "crf": 19,
        "save_metadata": true,
        "trim_to_audio": false,
        "pingpong": false,
        "save_output": false,
        "videopreview": {
          "hidden": false,
          "paused": false,
          "params": {
            "filename": "vitpose_00002.mp4",
            "subfolder": "",
            "type": "temp",
            "format": "video/h264-mp4",
            "frame_rate": 24,
            "workflow": "vitpose_00002.png",
            "fullpath": "E:\\staging\\ComfyTest\\ComfyUI\\temp\\vitpose_00002.mp4"
          }
        }
      }
    },
    {
      "id": 71,
      "type": "WanVideoAddSteadyDancerEmbeds",
      "pos": [
        974.8923491579199,
        392.5537037600541
      ],
      "size": [
        340.374609375,
        214
      ],
      "flags": {},
      "order": 48,
      "mode": 0,
      "inputs": [
        {
          "name": "embeds",
          "type": "WANVIDIMAGE_EMBEDS",
          "link": 93
        },
        {
          "name": "pose_latents_positive",
          "type": "LATENT",
          "link": 102
        },
        {
          "name": "pose_latents_negative",
          "shape": 7,
          "type": "LATENT",
          "link": null
        },
        {
          "name": "clip_vision_embeds",
          "shape": 7,
          "type": "WANVIDIMAGE_CLIPEMBEDS",
          "link": 115
        }
      ],
      "outputs": [
        {
          "name": "image_embeds",
          "type": "WANVIDIMAGE_EMBEDS",
          "links": [
            194
          ]
        }
      ],
      "properties": {
        "cnr_id": "ComfyUI-WanVideoWrapper",
        "ver": "772642b4f132a077f655ff24d11cb99ef108aff5",
        "Node name for S&R": "WanVideoAddSteadyDancerEmbeds"
      },
      "widgets_values": [
        1,
        1,
        0,
        1
      ]
    },
    {
      "id": 127,
      "type": "Note",
      "pos": [
        -828.1559188684124,
        -1360.1125375703239
      ],
      "size": [
        478.80782776762874,
        88
      ],
      "flags": {},
      "order": 18,
      "mode": 0,
      "inputs": [],
      "outputs": [],
      "properties": {
        "ue_properties": {
          "widget_ue_connectable": {},
          "version": "7.5.1",
          "input_ue_unconnectable": {}
        }
      },
      "widgets_values": [
        "https://huggingface.co/Kijai/WanVideo_comfy/tree/main/SteadyDancer\nhttps://huggingface.co/Kijai/WanVideo_comfy_fp8_scaled/tree/main/SteadyDancer"
      ],
      "color": "#432",
      "bgcolor": "#653"
    },
    {
      "id": 22,
      "type": "WanVideoModelLoader",
      "pos": [
        -834.6277690966749,
        -1172.6630946878518
      ],
      "size": [
        477.4410095214844,
        338
      ],
      "flags": {},
      "order": 27,
      "mode": 0,
      "inputs": [
        {
          "name": "compile_args",
          "shape": 7,
          "type": "WANCOMPILEARGS",
          "link": null
        },
        {
          "name": "block_swap_args",
          "shape": 7,
          "type": "BLOCKSWAPARGS",
          "link": null
        },
        {
          "name": "lora",
          "shape": 7,
          "type": "WANVIDLORA",
          "link": null
        },
        {
          "name": "vram_management_args",
          "shape": 7,
          "type": "VRAM_MANAGEMENTARGS",
          "link": null
        },
        {
          "name": "extra_model",
          "shape": 7,
          "type": "VACEPATH",
          "link": null
        },
        {
          "name": "fantasytalking_model",
          "shape": 7,
          "type": "FANTASYTALKINGMODEL",
          "link": null
        },
        {
          "name": "multitalk_model",
          "shape": 7,
          "type": "MULTITALKMODEL",
          "link": null
        },
        {
          "name": "fantasyportrait_model",
          "shape": 7,
          "type": "FANTASYPORTRAITMODEL",
          "link": null
        },
        {
          "name": "vace_model",
          "shape": 7,
          "type": "VACEPATH",
          "link": null
        }
      ],
      "outputs": [
        {
          "name": "model",
          "type": "WANVIDEOMODEL",
          "slot_index": 0,
          "links": [
            90
          ]
        }
      ],
      "properties": {
        "cnr_id": "ComfyUI-WanVideoWrapper",
        "ver": "d9b1f4d1a5aea91d101ae97a54714a5861af3f50",
        "Node name for S&R": "WanVideoModelLoader",
        "ue_properties": {
          "widget_ue_connectable": {},
          "version": "7.5.1",
          "input_ue_unconnectable": {}
        }
      },
      "widgets_values": [
        "Wan21_SteadyDancer_fp8_e4m3fn_scaled_KJ.safetensors",
        "fp16_fast",
        "disabled",
        "offload_device",
        "sageattn",
        "default"
      ],
      "color": "#223",
      "bgcolor": "#335"
    },
    {
      "id": 38,
      "type": "WanVideoVAELoader",
      "pos": [
        -830.7084410519781,
        -752.4044820163829
      ],
      "size": [
        372.7727966308594,
        106
      ],
      "flags": {},
      "order": 19,
      "mode": 0,
      "inputs": [
        {
          "name": "compile_args",
          "shape": 7,
          "type": "WANCOMPILEARGS",
          "link": null
        }
      ],
      "outputs": [
        {
          "name": "vae",
          "type": "WANVAE",
          "slot_index": 0,
          "links": [
            172
          ]
        }
      ],
      "properties": {
        "cnr_id": "ComfyUI-WanVideoWrapper",
        "ver": "d9b1f4d1a5aea91d101ae97a54714a5861af3f50",
        "Node name for S&R": "WanVideoVAELoader",
        "ue_properties": {
          "widget_ue_connectable": {},
          "version": "7.5.1",
          "input_ue_unconnectable": {}
        }
      },
      "widgets_values": [
        "Wan2_1_VAE_bf16.safetensors",
        "bf16",
        false
      ],
      "color": "#322",
      "bgcolor": "#533"
    },
    {
      "id": 69,
      "type": "WanVideoLoraSelect",
      "pos": [
        142.83325200322756,
        -1248.4198436353452
      ],
      "size": [
        583.5029907226562,
        176
      ],
      "flags": {},
      "order": 20,
      "mode": 0,
      "inputs": [
        {
          "name": "prev_lora",
          "shape": 7,
          "type": "WANVIDLORA",
          "link": null
        },
        {
          "name": "blocks",
          "shape": 7,
          "type": "SELECTEDBLOCKS",
          "link": null
        }
      ],
      "outputs": [
        {
          "name": "lora",
          "type": "WANVIDLORA",
          "links": [
            106
          ]
        }
      ],
      "properties": {
        "cnr_id": "ComfyUI-WanVideoWrapper",
        "ver": "6b9565ed6307168c45770ec08517d7df65b61e3f",
        "Node name for S&R": "WanVideoLoraSelect",
        "ue_properties": {
          "widget_ue_connectable": {},
          "version": "7.5.1",
          "input_ue_unconnectable": {}
        }
      },
      "widgets_values": [
        "lightx2v_I2V_14B_480p_cfg_step_distill_rank64_bf16.safetensors",
        1,
        false,
        false
      ],
      "color": "#223",
      "bgcolor": "#335"
    },
    {
      "id": 90,
      "type": "OnnxDetectionModelLoader",
      "pos": [
        -1015.2983215639625,
        394.43249299873725
      ],
      "size": [
        370.3601847372395,
        106
      ],
      "flags": {},
      "order": 21,
      "mode": 0,
      "inputs": [],
      "outputs": [
        {
          "name": "model",
          "type": "POSEMODEL",
          "links": [
            128
          ]
        }
      ],
      "properties": {
        "cnr_id": "ComfyUI-WanAnimatePreprocess",
        "ver": "2fcbcae7eec637fdc712fdec18e6266feb8ba3a7",
        "Node name for S&R": "OnnxDetectionModelLoader"
      },
      "widgets_values": [
        "vitpose_h_wholebody_model.onnx",
        "yolov10m.onnx",
        "CUDAExecutionProvider"
      ]
    },
    {
      "id": 76,
      "type": "LoadImage",
      "pos": [
        -1116.216142232196,
        -404.77190308791427
      ],
      "size": [
        307.65370061186877,
        519.0390204964908
      ],
      "flags": {},
      "order": 22,
      "mode": 0,
      "inputs": [],
      "outputs": [
        {
          "name": "IMAGE",
          "type": "IMAGE",
          "links": [
            122
          ]
        },
        {
          "name": "MASK",
          "type": "MASK",
          "links": null
        }
      ],
      "properties": {
        "cnr_id": "comfy-core",
        "ver": "0.3.75",
        "Node name for S&R": "LoadImage",
        "ue_properties": {
          "widget_ue_connectable": {},
          "version": "7.5.1",
          "input_ue_unconnectable": {}
        }
      },
      "widgets_values": [
        "s-l1200.jpg",
        "image"
      ]
    },
    {
      "id": 97,
      "type": "GetNode",
      "pos": [
        1739.8960154916208,
        -924.5630830271496
      ],
      "size": [
        210,
        60
      ],
      "flags": {
        "collapsed": true
      },
      "order": 23,
      "mode": 0,
      "inputs": [],
      "outputs": [
        {
          "name": "IMAGE",
          "type": "IMAGE",
          "links": [
            155
          ]
        }
      ],
      "title": "Get_start_frame",
      "properties": {
        "ue_properties": {
          "widget_ue_connectable": {},
          "version": "7.5.1",
          "input_ue_unconnectable": {}
        }
      },
      "widgets_values": [
        "start_frame"
      ],
      "color": "#2a363b",
      "bgcolor": "#3f5159"
    },
    {
      "id": 124,
      "type": "PrimitiveNode",
      "pos": [
        831.5300268213613,
        -284.8349824862588
      ],
      "size": [
        210,
        106
      ],
      "flags": {},
      "order": 24,
      "mode": 0,
      "inputs": [],
      "outputs": [
        {
          "name": "INT",
          "type": "INT",
          "widget": {
            "name": "seed"
          },
          "links": [
            207
          ]
        }
      ],
      "title": "seed",
      "properties": {
        "Run widget replace on values": false,
        "ue_properties": {
          "widget_ue_connectable": {},
          "version": "7.5.1",
          "input_ue_unconnectable": {}
        }
      },
      "widgets_values": [
        230951159472333,
        "randomize"
      ]
    },
    {
      "id": 75,
      "type": "VHS_LoadVideo",
      "pos": [
        -1028.2706578475534,
        602.150949921101
      ],
      "size": [
        296.0120268545073,
        802.0208291175888
      ],
      "flags": {},
      "order": 25,
      "mode": 0,
      "inputs": [
        {
          "name": "meta_batch",
          "shape": 7,
          "type": "VHS_BatchManager",
          "link": null
        },
        {
          "name": "vae",
          "shape": 7,
          "type": "VAE",
          "link": null
        }
      ],
      "outputs": [
        {
          "name": "IMAGE",
          "type": "IMAGE",
          "links": [
            129
          ]
        },
        {
          "name": "frame_count",
          "type": "INT",
          "links": []
        },
        {
          "name": "audio",
          "type": "AUDIO",
          "links": null
        },
        {
          "name": "video_info",
          "type": "VHS_VIDEOINFO",
          "links": null
        }
      ],
      "properties": {
        "cnr_id": "comfyui-videohelpersuite",
        "ver": "8550981384301e9bc5bfea83e5c2c75258102593",
        "Node name for S&R": "VHS_LoadVideo",
        "ue_properties": {
          "widget_ue_connectable": {},
          "version": "7.5.1",
          "input_ue_unconnectable": {}
        }
      },
      "widgets_values": {
        "video": "f.webm",
        "force_rate": 16,
        "custom_width": 480,
        "custom_height": 832,
        "frame_load_cap": 176,
        "skip_first_frames": 0,
        "select_every_nth": 1,
        "format": "AnimateDiff",
        "choose video to upload": "image",
        "videopreview": {
          "hidden": false,
          "paused": false,
          "params": {
            "filename": "f.webm",
            "type": "input",
            "format": "video/webm",
            "force_rate": 16,
            "custom_width": 480,
            "custom_height": 832,
            "frame_load_cap": 176,
            "skip_first_frames": 0,
            "select_every_nth": 1
          }
        }
      }
    },
    {
      "id": 92,
      "type": "WanVideoTextEncodeCached",
      "pos": [
        887.0207817526978,
        -1013.4887225568854
      ],
      "size": [
        450.14238398856924,
        384.84408195123683
      ],
      "flags": {},
      "order": 26,
      "mode": 0,
      "inputs": [
        {
          "name": "extender_args",
          "shape": 7,
          "type": "WANVIDEOPROMPTEXTENDER_ARGS",
          "link": null
        }
      ],
      "outputs": [
        {
          "name": "text_embeds",
          "type": "WANVIDEOTEXTEMBEDS",
          "links": [
            196
          ]
        },
        {
          "name": "negative_text_embeds",
          "type": "WANVIDEOTEXTEMBEDS",
          "links": null
        },
        {
          "name": "positive_prompt",
          "type": "STRING",
          "links": null
        }
      ],
      "properties": {
        "cnr_id": "ComfyUI-WanVideoWrapper",
        "ver": "394c7c13d24e5d3378e8259f9c2f9d33c49d985f",
        "Node name for S&R": "WanVideoTextEncodeCached",
        "ue_properties": {
          "widget_ue_connectable": {},
          "version": "7.5.1",
          "input_ue_unconnectable": {}
        }
      },
      "widgets_values": [
        "umt5-xxl-enc-bf16.safetensors",
        "bf16",
        "wiman dancing on stage",
        "JPEG",
        "disabled",
        true,
        "gpu"
      ],
      "color": "#332922",
      "bgcolor": "#593930"
    }
  ],
  "links": [
    [
      82,
      65,
      0,
      63,
      1,
      "WANVIDIMAGE_CLIPEMBEDS"
    ],
    [
      90,
      22,
      0,
      70,
      0,
      "WANVIDEOMODEL"
    ],
    [
      92,
      39,
      0,
      70,
      1,
      "BLOCKSWAPARGS"
    ],
    [
      93,
      63,
      0,
      71,
      0,
      "WANVIDIMAGE_EMBEDS"
    ],
    [
      102,
      72,
      0,
      71,
      1,
      "LATENT"
    ],
    [
      104,
      70,
      0,
      78,
      0,
      "WANVIDEOMODEL"
    ],
    [
      106,
      69,
      0,
      78,
      1,
      "WANVIDLORA"
    ],
    [
      114,
      81,
      0,
      82,
      1,
      "IMAGE"
    ],
    [
      115,
      82,
      0,
      71,
      3,
      "WANVIDIMAGE_CLIPEMBEDS"
    ],
    [
      122,
      76,
      0,
      68,
      0,
      "IMAGE"
    ],
    [
      127,
      89,
      0,
      88,
      0,
      "POSEDATA"
    ],
    [
      128,
      90,
      0,
      89,
      0,
      "POSEMODEL"
    ],
    [
      129,
      75,
      0,
      91,
      0,
      "IMAGE"
    ],
    [
      132,
      91,
      3,
      63,
      10,
      "INT"
    ],
    [
      133,
      91,
      0,
      89,
      1,
      "IMAGE"
    ],
    [
      136,
      88,
      0,
      77,
      0,
      "IMAGE"
    ],
    [
      153,
      68,
      0,
      96,
      0,
      "*"
    ],
    [
      154,
      96,
      0,
      63,
      2,
      "IMAGE"
    ],
    [
      155,
      97,
      0,
      79,
      0,
      "IMAGE"
    ],
    [
      156,
      91,
      1,
      98,
      0,
      "*"
    ],
    [
      157,
      98,
      0,
      89,
      3,
      "INT"
    ],
    [
      158,
      91,
      2,
      99,
      0,
      "*"
    ],
    [
      159,
      99,
      0,
      89,
      4,
      "INT"
    ],
    [
      161,
      100,
      0,
      77,
      3,
      "INT"
    ],
    [
      162,
      101,
      0,
      77,
      2,
      "INT"
    ],
    [
      163,
      102,
      0,
      68,
      2,
      "INT"
    ],
    [
      164,
      103,
      0,
      68,
      3,
      "INT"
    ],
    [
      165,
      104,
      0,
      63,
      8,
      "INT"
    ],
    [
      166,
      105,
      0,
      63,
      9,
      "INT"
    ],
    [
      167,
      98,
      0,
      88,
      1,
      "INT"
    ],
    [
      168,
      99,
      0,
      88,
      2,
      "INT"
    ],
    [
      169,
      59,
      0,
      106,
      0,
      "*"
    ],
    [
      171,
      107,
      0,
      82,
      0,
      "CLIP_VISION"
    ],
    [
      172,
      38,
      0,
      108,
      0,
      "*"
    ],
    [
      174,
      109,
      0,
      28,
      0,
      "WANVAE"
    ],
    [
      175,
      112,
      0,
      72,
      0,
      "WANVAE"
    ],
    [
      176,
      77,
      0,
      113,
      0,
      "*"
    ],
    [
      177,
      114,
      0,
      79,
      1,
      "IMAGE"
    ],
    [
      179,
      28,
      0,
      115,
      0,
      "IMAGE"
    ],
    [
      180,
      79,
      0,
      115,
      1,
      "IMAGE"
    ],
    [
      181,
      115,
      0,
      83,
      0,
      "IMAGE"
    ],
    [
      182,
      116,
      0,
      63,
      0,
      "WANVAE"
    ],
    [
      184,
      113,
      0,
      117,
      0,
      "IMAGE"
    ],
    [
      185,
      113,
      0,
      72,
      1,
      "IMAGE"
    ],
    [
      186,
      113,
      0,
      81,
      0,
      "IMAGE"
    ],
    [
      191,
      119,
      0,
      118,
      0,
      "SAMPLER_ARGS"
    ],
    [
      192,
      78,
      0,
      119,
      0,
      "WANVIDEOMODEL"
    ],
    [
      193,
      87,
      0,
      119,
      5,
      "WANVIDCONTEXT"
    ],
    [
      194,
      71,
      0,
      119,
      1,
      "WANVIDIMAGE_EMBEDS"
    ],
    [
      195,
      118,
      0,
      28,
      1,
      "LATENT"
    ],
    [
      196,
      92,
      0,
      119,
      2,
      "WANVIDEOTEXTEMBEDS"
    ],
    [
      205,
      123,
      0,
      119,
      17,
      "FLOAT"
    ],
    [
      206,
      122,
      3,
      119,
      19,
      "COMBO"
    ],
    [
      207,
      124,
      0,
      119,
      18,
      "INT"
    ],
    [
      208,
      128,
      0,
      65,
      0,
      "CLIP_VISION"
    ],
    [
      209,
      96,
      0,
      65,
      1,
      "IMAGE"
    ]
  ],
  "groups": [
    {
      "id": 1,
      "title": "Pose",
      "bounding": [
        -1172.0137082077667,
        278.7376420226755,
        2539.1966332900274,
        1239.3696389999159
      ],
      "color": "#3f789e",
      "font_size": 24,
      "flags": {}
    },
    {
      "id": 2,
      "title": "Models",
      "bounding": [
        -1348.1214363740485,
        -1447.2612623119862,
        2150.821271184883,
        811.4257822231209
      ],
      "color": "#88A",
      "font_size": 24,
      "flags": {}
    },
    {
      "id": 3,
      "title": "Reference image",
      "bounding": [
        -1184.7071710322302,
        -536.2416233014823,
        1623.835016750919,
        831.8098625752689
      ],
      "color": "#3f789e",
      "font_size": 24,
      "flags": {}
    }
  ],
  "config": {},
  "extra": {
    "ds": {
      "scale": 1.0834705943389074,
      "offset": [
        90.87072977036793,
        1217.1901976814981
      ]
    },
    "frontendVersion": "1.30.6",
    "node_versions": {
      "ComfyUI-WanVideoWrapper": "5a2383621a05825d0d0437781afcb8552d9590fd",
      "comfy-core": "0.3.26",
      "ComfyUI-KJNodes": "a5bd3c86c8ed6b83c55c2d0e7a59515b15a0137f",
      "ComfyUI-VideoHelperSuite": "0a75c7958fe320efcb052f1d9f8451fd20c730a8"
    },
    "VHS_latentpreview": false,
    "VHS_latentpreviewrate": 0,
    "VHS_MetadataImage": true,
    "VHS_KeepIntermediate": true,
    "workflowRendererVersion": "LG",
    "ue_links": []
  },
  "version": 0.4
}